{"name":"Octocat's Data Lab","tagline":"Octocat's Data Lab","body":"Octocat's Data Lab (Github Data Analysis)\r\n==============\r\n\r\nCMPE272 project from Group8 <br>\r\nTeam member: \r\n<table><tbody>\r\n   <tr>\r\n      <td>Nan Yu</td>\r\n      <td>Yulin Ye</td>\r\n      <td>Akash Patel</td>\r\n      <td>Ruiyun Zhou</td>\r\n   </tr>\r\n</tbody></table>\r\n\r\n<h3><a href='http://ec2-54-201-59-199.us-west-2.compute.amazonaws.com' target='_blank_'>Live Demo Here</a></h3>\r\n\r\n\r\n<span>\r\n<a href=\"http://octodex.github.com/labtocat\" class=\"preview-image\">\r\n<img src=\"http://octodex.github.com/images/labtocat.png\" align=\"center\" width=\"200px\" alt=\"the Labtocat\">\r\n</a>\r\n</span>\r\n\r\n<p><strong></strong></p><h4><strong>The goal of \"Octocat's data lab\" is to provide the visual analysis of the\r\nGitHub data to millions of users throughout the world using which they\r\ncan plan their future.</strong></h4><strong><br></strong>\r\n<strong>Main Functionality of “Octocat's data lab” is,</strong><br><br>\r\n<h5>1.\tLanguage Correlation: </h5> To analyze the data from GitHub and show user the\r\ncorrelation between various programming languages.<br>\r\n<h5>2.\tGeek Planet: </h5> To display the visual representation of the data being\r\ncommitted to GitHub from various parts of the world.<br>\r\n<h5>3.\tCoding Mood: </h5> What is the mood of the developer while working with\r\ndifferent programming languages?<br>\r\n<h5>4.\tHottest Technologies: </h5>  What hottest technologies are currently in the\r\nmarket?<br>\r\n<h5>5.\tLanguage Trends: </h5> Total number of commits made for a particular programming\r\nlanguage on a given day.<br>\r\n<p></p>\r\n\r\n","google":"","note":"Don't delete this file! It's used internally to help with page regeneration."}